foxclient/__init__.py
foxclient/api_client.py
foxclient/api_response.py
foxclient/configuration.py
foxclient/exceptions.py
foxclient/py.typed
foxclient/rest.py
foxclient/api/__init__.py
foxclient/api/device_api.py
foxclient/api/paste_api.py
foxclient/api/release_api.py
foxclient/api/stats_api.py
foxclient/models/__init__.py
foxclient/models/device_response.py
foxclient/models/global_stats_aggregation_model.py
foxclient/models/http_validation_error.py
foxclient/models/list_response_release_response.py
foxclient/models/list_response_short_device_response.py
foxclient/models/list_response_short_release_response.py
foxclient/models/list_response_str.py
foxclient/models/maintainer_short_model.py
foxclient/models/paste_input.py
foxclient/models/paste_output.py
foxclient/models/recovery_img_response.py
foxclient/models/release_groups_response.py
foxclient/models/release_response.py
foxclient/models/release_type.py
foxclient/models/releases_sort.py
foxclient/models/response_get_releases.py
foxclient/models/short_device_response.py
foxclient/models/short_release_response.py
foxclient/models/validation_error.py
foxclient/models/validation_error_loc_inner.py
foxclient-5.3.0.dist-info/METADATA
foxclient-5.3.0.dist-info/WHEEL
foxclient-5.3.0.dist-info/top_level.txt
foxclient-5.3.0.dist-info/RECORD
